webpack_boilerplate/__init__.py
webpack_boilerplate/apps.py
webpack_boilerplate/config.py
webpack_boilerplate/contrib/__init__.py
webpack_boilerplate/contrib/jinja2ext.py
webpack_boilerplate/exceptions.py
webpack_boilerplate/frontend_template/cookiecutter.json
webpack_boilerplate/frontend_template/hooks/post_gen_project.py
webpack_boilerplate/frontend_template/{{cookiecutter.project_slug}}/.babelrc
webpack_boilerplate/frontend_template/{{cookiecutter.project_slug}}/.browserslistrc
webpack_boilerplate/frontend_template/{{cookiecutter.project_slug}}/.eslintrc
webpack_boilerplate/frontend_template/{{cookiecutter.project_slug}}/.gitignore
webpack_boilerplate/frontend_template/{{cookiecutter.project_slug}}/.nvmrc
webpack_boilerplate/frontend_template/{{cookiecutter.project_slug}}/.stylelintrc.json
webpack_boilerplate/frontend_template/{{cookiecutter.project_slug}}/README.md
webpack_boilerplate/frontend_template/{{cookiecutter.project_slug}}/package-lock.json
webpack_boilerplate/frontend_template/{{cookiecutter.project_slug}}/package.json
webpack_boilerplate/frontend_template/{{cookiecutter.project_slug}}/postcss.config.js
webpack_boilerplate/frontend_template/{{cookiecutter.project_slug}}/src/application/app.js
webpack_boilerplate/frontend_template/{{cookiecutter.project_slug}}/src/application/app2.js
webpack_boilerplate/frontend_template/{{cookiecutter.project_slug}}/src/components/sidebar.js
webpack_boilerplate/frontend_template/{{cookiecutter.project_slug}}/src/styles/index.scss
webpack_boilerplate/frontend_template/{{cookiecutter.project_slug}}/vendors/.gitkeep
webpack_boilerplate/frontend_template/{{cookiecutter.project_slug}}/vendors/images/.gitkeep
webpack_boilerplate/frontend_template/{{cookiecutter.project_slug}}/vendors/images/sample.jpg
webpack_boilerplate/frontend_template/{{cookiecutter.project_slug}}/vendors/images/webpack.png
webpack_boilerplate/frontend_template/{{cookiecutter.project_slug}}/webpack/webpack.common.js
python_webpack_boilerplate-1.0.2.dist-info/LICENSE
python_webpack_boilerplate-1.0.2.dist-info/WHEEL
python_webpack_boilerplate-1.0.2.dist-info/METADATA
python_webpack_boilerplate-1.0.2.dist-info/RECORD
