Metadata-Version: 2.1
Name: python-webpack-boilerplate
Version: 1.0.2
Summary: Jump start frontend project bundled by Webpack
Home-page: https://github.com/AccordBox/python-webpack-boilerplate
License: MIT
Keywords: python,django,flask,webpack
Author: Michael Yin
Author-email: michaelyin@accordbox.com
Requires-Python: >=3.6,<4.0
Classifier: Environment :: Web Environment
Classifier: Framework :: Django
Classifier: Framework :: Flask
Classifier: License :: OSI Approved :: MIT License
Classifier: Programming Language :: Python :: 3
Classifier: Programming Language :: Python :: 3.10
Classifier: Programming Language :: Python :: 3.6
Classifier: Programming Language :: Python :: 3.7
Classifier: Programming Language :: Python :: 3.8
Classifier: Programming Language :: Python :: 3.9
Classifier: Topic :: Software Development :: Libraries
Classifier: Topic :: Utilities
Requires-Dist: cookiecutter (>=1.7.0)
